README.rst
setup.py
OQToolsUI.egg-info/PKG-INFO
OQToolsUI.egg-info/SOURCES.txt
OQToolsUI.egg-info/dependency_links.txt
OQToolsUI.egg-info/entry_points.txt
OQToolsUI.egg-info/requires.txt
OQToolsUI.egg-info/top_level.txt
oqtoolsui/__init__.py
oqtoolsui/common/__init__.py
oqtoolsui/common/entities.py
oqtoolsui/common/math_utils.py
oqtoolsui/common/values.py
oqtoolsui/common/xml_utils.py
oqtoolsui/controllers/__init__.py
oqtoolsui/controllers/asciiconvertercontroller.py
oqtoolsui/controllers/convertercontroller.py
oqtoolsui/controllers/inputfilegencontroller.py
oqtoolsui/controllers/nrmlconvertercontroller.py
oqtoolsui/converters/__init__.py
oqtoolsui/converters/convert_SourceModel_Nrml03to04.py
oqtoolsui/converters/gml.py
oqtoolsui/converters/gmt.py
oqtoolsui/converters/meanmfdfunctions.py
oqtoolsui/converters/nrml03.py
oqtoolsui/converters/nrml04.py
oqtoolsui/converters/plot_source_model.py
oqtoolsui/converters/shapefileconverter.py
oqtoolsui/converters/source_model.py
oqtoolsui/oqtools/__init__.py
oqtoolsui/oqtools/intensityLevels.txt
oqtoolsui/oqtools/job.ini.template
oqtoolsui/oqtools/main.py
oqtoolsui/oqtools/main_window.py
oqtoolsui/ui/__init__.py
oqtoolsui/ui/asciiconverterwindow.py
oqtoolsui/ui/inputfilegenwindow.py
oqtoolsui/ui/nrmlconverterwindow.py
oqtoolsui/ui/panels.py
oqtoolsui/ui/shapeconverterwindow.py
oqtoolsui/ui/widgets.py