Metadata-Version: 1.1
Name: OQToolsUI
Version: 1.0.5
Summary: UI for openquake
Home-page: http://github.com/ocozalp/OQToolsUI
Author: Orhan Can Ozalp
Author-email: ozalp.orhan@gmail.com
License: GNU Affero General Public License v3
Platform: UNKNOWN
Classifier: Development Status :: 4 - Beta
Classifier: Environment :: X11 Applications :: Qt
Classifier: Intended Audience :: Education
Classifier: Intended Audience :: Science/Research
Classifier: License :: OSI Approved :: GNU Affero General Public License v3
Classifier: Natural Language :: English
Classifier: Operating System :: POSIX :: Linux
Classifier: Programming Language :: Python :: 2.7
Classifier: Programming Language :: Python :: Implementation :: CPython
Classifier: Topic :: Education
Classifier: Topic :: Scientific/Engineering
